[{"id": 461,"commune_name": "مهدية","daira_name": "مهدية"},{"id": 447,"commune_name": "عين دزاريت","daira_name": "مهدية"},{"id": 472,"commune_name": "السبعين","daira_name": "مهدية"},{"id": 455,"commune_name": "الفايجة","daira_name": "السوقر"},{"id": 475,"commune_name": "سي عبد الغني","daira_name": "السوقر"},{"id": 480,"commune_name": "السوقر","daira_name": "السوقر"},{"id": 485,"commune_name": "توسنينة","daira_name": "السوقر"},{"id": 465,"commune_name": "مغيلة","daira_name": "مغيلة"},{"id": 473,"commune_name": "السبت","daira_name": "مغيلة"},{"id": 479,"commune_name": "سيدي حسني","daira_name": "مغيلة"},{"id": 448,"commune_name": "عين الحديد","daira_name": "فرندة"},{"id": 456,"commune_name": "فرندة","daira_name": "فرندة"},{"id": 482,"commune_name": "تخمرت","daira_name": "فرندة"},{"id": 449,"commune_name": "عين كرمس","daira_name": "عين كرمس"},{"id": 453,"commune_name": "جبيلات الرصفاء","daira_name": "عين كرمس"},{"id": 460,"commune_name": "مادنة","daira_name": "عين كرمس"},{"id": 463,"commune_name": "مدريسة","daira_name": "عين كرمس"},{"id": 476,"commune_name": "سيدي عبد الرحمن","daira_name": "عين كرمس"},{"id": 459,"commune_name": "قصر الشلالة","daira_name": "قصر الشلالة"},{"id": 457,"commune_name": "قرطوفة","daira_name": "رحوية"},{"id": 474,"commune_name": "سرغين","daira_name": "قصر الشلالة"},{"id": 486,"commune_name": "زمالة  الأمير عبد القادر","daira_name": "قصر الشلالة"},{"id": 469,"commune_name": "وادي ليلي","daira_name": "وادي ليلي"},{"id": 477,"commune_name": "سيدي علي ملال","daira_name": "وادي ليلي"},{"id": 454,"commune_name": "جيلالي بن عمار","daira_name": "مشرع الصفا"},{"id": 462,"commune_name": "مشرع الصفا","daira_name": "مشرع الصفا"},{"id": 481,"commune_name": "تاقدمت","daira_name": "مشرع الصفا"},{"id": 450,"commune_name": "بوقرة","daira_name": "حمادية"},{"id": 458,"commune_name": "حمادية","daira_name": "حمادية"},{"id": 471,"commune_name": "الرشايقة","daira_name": "حمادية"},{"id": 484,"commune_name": "تيدة","daira_name": "وادي ليلي"},{"id": 467,"commune_name": "الناظورة","daira_name": "مهدية"},{"id": 483,"commune_name": "تيارت","daira_name": "تيارت"},{"id": 464,"commune_name": "مدروسة","daira_name": "مدروسة"},{"id": 466,"commune_name": "ملاكو","daira_name": "مدروسة"},{"id": 478,"commune_name": "سيدي بختي","daira_name": "مدروسة"},{"id": 446,"commune_name": "عين الذهب","daira_name": "عين الذهب"},{"id": 451,"commune_name": "شحيمة","daira_name": "عين الذهب"},{"id": 468,"commune_name": "النعيمة","daira_name": "عين الذهب"},{"id": 445,"commune_name": "عين بوشقيف","daira_name": "دحموني"},{"id": 452,"commune_name": "دحموني","daira_name": "دحموني"},{"id": 470,"commune_name": "الرحوية","daira_name": "رحوية"}]