[{"id": 1369,"commune_name": "حجوط","daira_name": "حجوط"},{"id": 1375,"commune_name": "مراد","daira_name": "حجوط"},{"id": 1374,"commune_name": "مناصر","daira_name": "سيدي أعمر"},{"id": 1355,"commune_name": "أغبال","daira_name": "قوراية"},{"id": 1377,"commune_name": "الناظور","daira_name": "سيدي أعمر"},{"id": 1381,"commune_name": "سيدي عامر","daira_name": "سيدي أعمر"},{"id": 1368,"commune_name": "قوراية","daira_name": "قوراية"},{"id": 1376,"commune_name": "مسلمون","daira_name": "قوراية"},{"id": 1364,"commune_name": "شرشال","daira_name": "شرشال"},{"id": 1370,"commune_name": "حجرة النص","daira_name": "شرشال"},{"id": 1378,"commune_name": "سيدي غيلاس","daira_name": "شرشال"},{"id": 1365,"commune_name": "الداموس","daira_name": "الداموس"},{"id": 1373,"commune_name": "الأرهاط","daira_name": "الداموس"},{"id": 1367,"commune_name": "فوكة","daira_name": "فوكة"},{"id": 1357,"commune_name": "عين تاقورايت","daira_name": "بواسماعيل"},{"id": 1360,"commune_name": "بوهارون","daira_name": "بواسماعيل"},{"id": 1361,"commune_name": "بواسماعيل","daira_name": "بواسماعيل"},{"id": 1371,"commune_name": "خميستي","daira_name": "بواسماعيل"},{"id": 1356,"commune_name": "أحمر العين","daira_name": "أحمر العين"},{"id": 1362,"commune_name": "بورقيقة","daira_name": "أحمر العين"},{"id": 1366,"commune_name": "دواودة","daira_name": "فوكة"},{"id": 1379,"commune_name": "سيدي راشد","daira_name": "أحمر العين"},{"id": 1358,"commune_name": "الحطاطبة","daira_name": "القليعة"},{"id": 1363,"commune_name": "الشعيبة","daira_name": "القليعة"},{"id": 1372,"commune_name": "القليعة","daira_name": "القليعة"},{"id": 1380,"commune_name": "سيدي سميان","daira_name": "شرشال"},{"id": 1382,"commune_name": "تيبازة","daira_name": "تيبازة"},{"id": 1359,"commune_name": "بني ميلك","daira_name": "الداموس"}]